fastj2/__init__.py
fastj2/core.py
fastj2/css_documentation.py
fastj2/html_header.py
fastj2/html_render_error.py
fastj2/js_documentation.py
fastj2/themes/basic/0-basic/badges.css
fastj2/themes/basic/0-basic/body.css
fastj2/themes/basic/0-basic/containers.css
fastj2/themes/basic/0-basic/grid.css
fastj2/themes/basic/0-basic/menus.css
fastj2/themes/basic/0-basic/text.css
fastj2/themes/basic/vars.css
fastj2/themes.py
fastj2-0.1.231.dist-info/METADATA
fastj2-0.1.231.dist-info/WHEEL
fastj2-0.1.231.dist-info/RECORD
